nasty_utils/__init__.py
nasty_utils/_version.py
nasty_utils/datetime_.py
nasty_utils/download.py
nasty_utils/io_.py
nasty_utils/logging_.py
nasty_utils/logging_settings.py
nasty_utils/misc.py
nasty_utils/program.py
nasty_utils/py.typed
nasty_utils/settings.py
nasty_utils/typing_.py
nasty_utils/_util/__init__.py
nasty_utils/_util/argparse_.py
nasty_utils-0.1.0.dist-info/LICENSE
nasty_utils-0.1.0.dist-info/METADATA
nasty_utils-0.1.0.dist-info/WHEEL
nasty_utils-0.1.0.dist-info/top_level.txt
nasty_utils-0.1.0.dist-info/zip-safe
nasty_utils-0.1.0.dist-info/RECORD
